aeidon/__init__.py
aeidon/calculator.py
aeidon/clipboard.py
aeidon/containers.py
aeidon/countries.py
aeidon/deco.py
aeidon/delegate.py
aeidon/encodings.py
aeidon/enum.py
aeidon/enums.py
aeidon/errors.py
aeidon/file.py
aeidon/finder.py
aeidon/i18n.py
aeidon/languages.py
aeidon/liner.py
aeidon/locales.py
aeidon/markup.py
aeidon/markupconv.py
aeidon/metadata.py
aeidon/mutables.py
aeidon/observable.py
aeidon/parser.py
aeidon/paths.py
aeidon/pattern.py
aeidon/patternman.py
aeidon/position.py
aeidon/project.py
aeidon/revertable.py
aeidon/scripts.py
aeidon/singleton.py
aeidon/spell.py
aeidon/subtitle.py
aeidon/temp.py
aeidon/unittest.py
aeidon/util.py
aeidon/agents/__init__.py
aeidon/agents/clipboard.py
aeidon/agents/edit.py
aeidon/agents/format.py
aeidon/agents/open.py
aeidon/agents/position.py
aeidon/agents/preview.py
aeidon/agents/register.py
aeidon/agents/save.py
aeidon/agents/search.py
aeidon/agents/set.py
aeidon/agents/text.py
aeidon/agents/util.py
aeidon/data/headers/ass
aeidon/data/headers/lrc
aeidon/data/headers/microdvd
aeidon/data/headers/ssa
aeidon/data/headers/subviewer2
aeidon/data/headers/webvtt
aeidon/data/patterns/Latn-en-US.common-error.conf
aeidon/data/patterns/Latn-en-US.common-error.in
aeidon/data/patterns/Latn-en.capitalization.conf
aeidon/data/patterns/Latn-en.capitalization.in
aeidon/data/patterns/Latn-en.common-error.conf
aeidon/data/patterns/Latn-en.common-error.in
aeidon/data/patterns/Latn-en.hearing-impaired.conf
aeidon/data/patterns/Latn-en.hearing-impaired.in
aeidon/data/patterns/Latn-en.line-break.conf
aeidon/data/patterns/Latn-en.line-break.in
aeidon/data/patterns/Latn-fi.common-error.conf
aeidon/data/patterns/Latn-fi.common-error.in
aeidon/data/patterns/Latn-fr.common-error.conf
aeidon/data/patterns/Latn-fr.common-error.in
aeidon/data/patterns/Latn.capitalization.conf
aeidon/data/patterns/Latn.capitalization.in
aeidon/data/patterns/Latn.common-error.conf
aeidon/data/patterns/Latn.common-error.in
aeidon-1.15.dist-info/AUTHORS.md
aeidon-1.15.dist-info/COPYING
aeidon-1.15.dist-info/METADATA
aeidon-1.15.dist-info/WHEEL
aeidon-1.15.dist-info/top_level.txt
aeidon-1.15.dist-info/RECORD
