Metadata-Version: 2.1
Name: aeidon
Version: 1.15
Summary: Reading, writing and manipulating text-based subtitle files
Home-page: https://github.com/otsaloma/gaupol
Author: Osmo Salomaa
Author-email: otsaloma@iki.fi
License: GPL
Requires-Python: >=3.5.0
License-File: COPYING
License-File: AUTHORS.md
Requires-Dist: charset-normalizer >2.0
